signalsnap/__init__.py
signalsnap/analysis.py
signalsnap/plot_config.py
signalsnap/spectrum_calculator.py
signalsnap/spectrum_config.py
signalsnap/spectrum_plotter.py
signalsnap/tests/__init__.py
signalsnap/tests/generate_test_data.ipynb
signalsnap/tests/test.ipynb
signalsnap/tests/test_calc_spec.py
signalsnap/tests/data/data_for_test_calc_spec.pkl
signalsnap-1.0.21.dist-info/METADATA
signalsnap-1.0.21.dist-info/WHEEL
signalsnap-1.0.21.dist-info/licenses/LICENSE
signalsnap-1.0.21.dist-info/RECORD
