Metadata-Version: 2.4
Name: signalsnap
Version: 1.0.21
Summary: Spectra at your fingertips
Project-URL: Homepage, https://github.com/MarkusSifft/SignalSnap
Project-URL: Bug Tracker, https://github.com/MarkusSifft/SignalSnap/issues
Author-email: Markus Sifft <markus.sifft@rub.de>
License-File: LICENSE
Keywords: analysis,signal processing,spectra
Classifier: Development Status :: 5 - Production/Stable
Classifier: Intended Audience :: Science/Research
Classifier: License :: OSI Approved :: BSD License
Classifier: Operating System :: OS Independent
Classifier: Programming Language :: Python
Classifier: Programming Language :: Python :: 3
Classifier: Topic :: Scientific/Engineering
Requires-Python: >3.8
Requires-Dist: arrayfire
Requires-Dist: h5py
Requires-Dist: matplotlib
Requires-Dist: numba
Requires-Dist: numpy
Requires-Dist: plotly
Requires-Dist: scipy
Requires-Dist: tqdm
